Workbook

Sheet Ventas
A1: Detalle de ventas con Boleta | L1: diferencia
A3: Fecha | B3: Z | C3: Boletas | D3: Monto | E3: Repetir Monto | F3: Cuadratura Cero | G3: Observación
A4: 44409 | F4: =E4-D4 -> 0
A5: 44410 | F5: =E5-D5 -> 0
A6: 44411 | F6: =E6-D6 -> 0
A7: 44412 | F7: =E7-D7 -> 0
A8: 44413 | F8: =E8-D8 -> 0
A9: 44414 | F9: =E9-D9 -> 0
A10: 44415 | F10: =E10-D10 -> 0
A11: 44416 | F11: =E11-D11 -> 0
A12: 44417 | F12: =E12-D12 -> 0
A13: 44418 | F13: =E13-D13 -> 0
A14: 44419 | F14: =E14-D14 -> 0
A15: 44420 | F15: =E15-D15 -> 0
... A34: 44439 | F34: =E34-D34 -> 0
F35: =E35-D35 -> 0
D91: =SUM(D4:D90) -> 0
B93: =SUM(D4:D36) -> 0 | J93: =D33-D32 -> 0

Sheet Transbank
A1: Detalle transbank | L1: diferencia
A3: Fecha | B3: Monto | C3: Repetir Monto | D3: Cuadratura Cero | E3: Debito | F3: Credito | G3: Observación: Debito o Crédito | H3: RCtobalaba
A4: 44409 | B4: =E4+F4 -> 0 | C4: =+B4 -> 0 | D4: =C4-B4 -> 0
A5: 44410 | B5: =E5+F5 -> 0 | C5: =+B5 -> 0 | D5: =C5-B5 -> 0
A6: 44411 | B6: =E6+F6 -> 0 | C6: =+B6 -> 0 | D6: =C6-B6 -> 0
A7: 44412 | B7: =E7+F7 -> 0 | C7: =+B7 -> 0 | D7: =C7-B7 -> 0
A8: 44413 | B8: =E8+F8 -> 0 | C8: =+B8 -> 0 | D8: =C8-B8 -> 0
A9: 44414 | B9: =E9+F9 -> 0 | C9: =+B9 -> 0 | D9: =C9-B9 -> 0
A10: 44415 | B10: =E10+F10 -> 0 | C10: =+B10 -> 0 | D10: =C10-B10 -> 0
A11: 44416 | B11: =E11+F11 -> 0 | C11: =+B11 -> 0 | D11: =C11-B11 -> 0
A12: 44417 | B12: =E12+F12 -> 0 | C12: =+B12 -> 0 | D12: =C12-B12 -> 0
A13: 44418 | B13: =E13+F13 -> 0 | C13: =+B13 -> 0 | D13: =C13-B13 -> 0
A14: 44419 | B14: =E14+F14 -> 0 | C14: =+B14 -> 0 | D14: =C14-B14 -> 0
A15: 44420 | B15: =E15+F15 -> 0 | C15: =+B15 -> 0 | D15: =C15-B15 -> 0
... A34: 44439 | B34: =E34+F34 -> 0 | C34: =+B34 -> 0 | D34: =C34-B34 -> 0
B35: =+E35+F35 -> 0 | C35: =+B35 -> 0 | D35: =C35-B35 -> 0
B92: =SUM(B4:B91) -> 0

Sheet Cheques y trans.
A1: Detalle Vales Tickets . Sodexo Recibidos | L1: diferencia
A3: Fecha | B3: Monto | C3: Repetir Monto | D3: Cuadratura Cero | E3: Observación
A4: 44409 | B4: 0 | C4: 0 | D4: =C4-B4 -> 0
A5: 44410 | B5: 0 | C5: 0 | D5: =C5-B5 -> 0
A6: 44411 | B6: 0 | C6: 0 | D6: =C6-B6 -> 0
A7: 44412 | B7: 0 | C7: 0 | D7: =C7-B7 -> 0
A8: 44413 | B8: 0 | C8: 0 | D8: =C8-B8 -> 0
A9: 44414 | B9: 0 | C9: 0 | D9: =C9-B9 -> 0
A10: 44415 | B10: 0 | C10: 0 | D10: =C10-B10 -> 0
A11: 44416 | B11: 0 | C11: 0 | D11: =C11-B11 -> 0
A12: 44417 | B12: 0 | C12: 0 | D12: =C12-B12 -> 0
A13: 44418 | B13: 0 | C13: 0 | D13: =C13-B13 -> 0
A14: 44419 | B14: 0 | C14: 0 | D14: =C14-B14 -> 0
A15: 44420 | B15: 0 | C15: 0 | D15: =C15-B15 -> 0
... A33: 44438 | B33: 0 | C33: 0 | D33: =C33-B33 -> 0
A34: 44439

Sheet Retiros
A1: Retiros caja
A3: Fecha | B3: Monto | C3: Monto | D3: Cuadratura Cero | E3: Observación | F3: gatos domingo | G3: gastos domingo
G4: =SUM(F4:F512) -> 0
R30: ,
D106: =B106-C106 -> 0
D107: =B107-C107 -> 0
D108: =B108-C108 -> 0
D109: =B109-C109 -> 0
D110: =B110-C110 -> 0
D111: =B111-C111 -> 0
D112: =B112-C112 -> 0
D113: =B113-C113 -> 0
D114: =B114-C114 -> 0
D115: =B115-C115 -> 0
D116: =B116-C116 -> 0
D117: =B117-C117 -> 0
... D200: =B200-C200 -> 0
D447: =C447-B447 -> 0
D448: =C448-B448 -> 0
D449: =C449-B449 -> 0
D450: =C450-B450 -> 0
D451: =C451-B451 -> 0
D452: =C452-B452 -> 0
D453: =C453-B453 -> 0
D454: =C454-B454 -> 0
D455: =C455-B455 -> 0
D456: =C456-B456 -> 0
D457: =C457-B457 -> 0
D458: =C458-B458 -> 0
... D582: =C582-B582 -> 0

Sheet Cuadratura
A1: Dia | B1: Boleta inicial | C1: Boleta Final | D1: monto ventas | E1: Monto ventas Sin IVA | F1: Transbank | G1: monto sodexo y otros | H1: retiros | I1: saldo caja inicio | J1: Saldo Efectivo | K1: Digite el Efectivo en Caja Real | L1: diferencia | M1: Monto a Retirar | O1: entegado
A2: 44409 | D2: =+Ventas!D4 -> 0 | E2: =D2/1.19 -> 0 | F2: =+Transbank!B4 -> 0 | G2: =+Cuadratura!$K$35 -> 0 | H2: =VLOOKUP(A2,Resumen!$G$3:$H$54,2,0) -> #N/A | I2: 44080 | J2: =+D2-F2-H2+I2 -> #N/A | L2: =+K2-J2 -> #N/A
A3: 44410 | D3: =+Ventas!D5 -> 0 | E3: =D3/1.19 -> 0 | F3: =+Transbank!B5 -> 0 | G3: =+Cuadratura!$K$35 -> 0 | H3: =VLOOKUP(A3,Resumen!$G$3:$H$54,2,0) -> #N/A | I3: =K2-M2 -> 0 | J3: =+D3-F3-H3+I3 -> #N/A | L3: =+K3-J3 -> #N/A
A4: 44411 | D4: =+Ventas!D6 -> 0 | E4: =D4/1.19 -> 0 | F4: =+Transbank!B6 -> 0 | G4: =+Cuadratura!$K$35 -> 0 | H4: =VLOOKUP(A4,Resumen!$G$3:$H$54,2,0) -> #N/A | I4: =K3-M3 -> 0 | J4: =+D4-F4-H4+I4 -> #N/A | L4: =+K4-J4 -> #N/A
A5: 44412 | D5: =+Ventas!D7 -> 0 | E5: =D5/1.19 -> 0 | F5: =+Transbank!B7 -> 0 | G5: =+Cuadratura!$K$35 -> 0 | H5: =VLOOKUP(A5,Resumen!$G$3:$H$54,2,0) -> #N/A | I5: =K4-M4 -> 0 | J5: =+D5-F5-H5+I5 -> #N/A | L5: =+K5-J5 -> #N/A
A6: 44413 | D6: =+Ventas!D8 -> 0 | E6: =D6/1.19 -> 0 | F6: =+Transbank!B8 -> 0 | G6: =+Cuadratura!$K$35 -> 0 | H6: =VLOOKUP(A6,Resumen!$G$3:$H$54,2,0) -> #N/A | I6: =K5-M5 -> 0 | J6: =+D6-F6-H6+I6 -> #N/A | L6: =+K6-J6 -> #N/A
A7: 44414 | D7: =+Ventas!D9 -> 0 | E7: =D7/1.19 -> 0 | F7: =+Transbank!B9 -> 0 | G7: =+Cuadratura!$K$35 -> 0 | H7: =VLOOKUP(A7,Resumen!$G$3:$H$54,2,0) -> #N/A | I7: =K6-M6 -> 0 | J7: =+D7-F7-H7+I7 -> #N/A | L7: =+K7-J7 -> #N/A
A8: 44415 | D8: =+Ventas!D10 -> 0 | E8: =D8/1.19 -> 0 | F8: =+Transbank!B10 -> 0 | G8: =+Cuadratura!$K$35 -> 0 | H8: =VLOOKUP(A8,Resumen!$G$3:$H$54,2,0) -> #N/A | I8: =K7-M7 -> 0 | J8: =+D8-F8-H8+I8 -> #N/A | L8: =+K8-J8 -> #N/A
A9: 44416 | D9: =+Ventas!D11 -> 0 | E9: =D9/1.19 -> 0 | F9: =+Transbank!B11 -> 0 | G9: =+Cuadratura!$K$35 -> 0 | H9: =VLOOKUP(A9,Resumen!$G$3:$H$54,2,0) -> #N/A | I9: =K8-M8 -> 0 | J9: =+D9-F9-H9+I9 -> #N/A | L9: =+K9-J9 -> #N/A
A10: 44417 | D10: =+Ventas!D12 -> 0 | E10: =D10/1.19 -> 0 | F10: =+Transbank!B12 -> 0 | G10: =+Cuadratura!$K$35 -> 0 | H10: =VLOOKUP(A10,Resumen!$G$3:$H$54,2,0) -> #N/A | I10: =K9-M9 -> 0 | J10: =+D10-F10-H10+I10 -> #N/A | L10: =+K10-J10 -> #N/A
A11: 44418 | D11: =+Ventas!D13 -> 0 | E11: =D11/1.19 -> 0 | F11: =+Transbank!B13 -> 0 | G11: =+Cuadratura!$K$35 -> 0 | H11: =VLOOKUP(A11,Resumen!$G$3:$H$54,2,0) -> #N/A | I11: =K10-M10 -> 0 | J11: =+D11-F11-H11+I11 -> #N/A | L11: =+K11-J11 -> #N/A
A12: 44419 | D12: =+Ventas!D14 -> 0 | E12: =D12/1.19 -> 0 | F12: =+Transbank!B14 -> 0 | G12: =+Cuadratura!$K$35 -> 0 | H12: =VLOOKUP(A12,Resumen!$G$3:$H$54,2,0) -> #N/A | I12: =K11-M11 -> 0 | J12: =+D12-F12-H12+I12 -> #N/A | L12: =+K12-J12 -> #N/A
A13: 44420 | D13: =+Ventas!D15 -> 0 | E13: =D13/1.19 -> 0 | F13: =+Transbank!B15 -> 0 | G13: =+Cuadratura!$K$35 -> 0 | H13: =VLOOKUP(A13,Resumen!$G$3:$H$54,2,0) -> #N/A | I13: =K12-M12 -> 0 | J13: =+D13-F13-H13+I13 -> #N/A | L13: =+K13-J13 -> #N/A
A14: 44421 | D14: =+Ventas!D16 -> 0 | E14: =D14/1.19 -> 0 | F14: =+Transbank!B16 -> 0 | G14: =+Cuadratura!$K$35 -> 0 | H14: =VLOOKUP(A14,Resumen!$G$3:$H$54,2,0) -> #N/A | I14: =K13-M13 -> 0 | J14: =+D14-F14-H14+I14 -> #N/A | L14: =+K14-J14 -> #N/A
... A25: 44432 | D25: =+Ventas!D27 -> 0 | E25: =D25/1.19 -> 0 | F25: =+Transbank!B27 -> 0 | G25: =+Cuadratura!$K$35 -> 0 | H25: =VLOOKUP(A25,Resumen!$G$3:$H$54,2,0) -> #N/A | I25: =K24-M24 -> 0 | J25: =+D25-F25-H25+I25 -> #N/A | L25: =+K25-J25 -> #N/A
A26: 44433 | D26: =+Ventas!D28 -> 0 | E26: =D26/1.19 -> 0 | F26: =+Transbank!B28 -> 0 | G26: =+Cuadratura!$K$35 -> 0 | H26: =VLOOKUP(A26,Resumen!$G$3:$H$54,2,0) -> #N/A | I26: =K25-M25 -> 0 | J26: =+D26-F26-H26+I26 -> #N/A | L26: =+K26-J26 -> #N/A | N26: ,
A27: 44434 | D27: =+Ventas!D29 -> 0 | E27: =D27/1.19 -> 0 | F27: =+Transbank!B29 -> 0 | G27: =+Cuadratura!$K$35 -> 0 | H27: =VLOOKUP(A27,Resumen!$G$3:$H$54,2,0) -> #N/A | I27: =K26-M26 -> 0 | J27: =+D27-F27-H27+I27 -> #N/A | L27: =+K27-J27 -> #N/A
A28: 44435 | D28: =+Ventas!D30 -> 0 | E28: =D28/1.19 -> 0 | F28: =+Transbank!B30 -> 0 | G28: =+Cuadratura!$K$35 -> 0 | H28: =VLOOKUP(A28,Resumen!$G$3:$H$54,2,0) -> #N/A | I28: =K27-M27 -> 0 | J28: =+D28-F28-H28+I28 -> #N/A | L28: =+K28-J28 -> #N/A
A29: 44436 | D29: =+Ventas!D31 -> 0 | E29: =D29/1.19 -> 0 | F29: =+Transbank!B31 -> 0 | G29: =+Cuadratura!$K$35 -> 0 | H29: =VLOOKUP(A29,Resumen!$G$3:$H$54,2,0) -> #N/A | I29: =K28-M28 -> 0 | J29: =+D29-F29-H29+I29 -> #N/A | L29: =+K29-J29 -> #N/A
A30: 44437 | D30: =+Ventas!D32 -> 0 | E30: =D30/1.19 -> 0 | F30: =+Transbank!B32 -> 0 | G30: =+Cuadratura!$K$35 -> 0 | H30: =VLOOKUP(A30,Resumen!$G$3:$H$54,2,0) -> #N/A | I30: =K29-M29 -> 0 | J30: =+D30-F30-H30+I30 -> #N/A | L30: =+K30-J30 -> #N/A
A31: 44438 | D31: =+Ventas!D33 -> 0 | E31: =D31/1.19 -> 0 | F31: =+Transbank!B33 -> 0 | G31: =+Cuadratura!$K$35 -> 0 | H31: =VLOOKUP(A31,Resumen!$G$3:$H$54,2,0) -> #N/A | I31: =K30-M30 -> 0 | J31: =+D31-F31-H31+I31 -> #N/A | L31: =+K31-J31 -> #N/A
A32: 44439 | D32: =+Ventas!D34 -> 0 | E32: =D32/1.19 -> 0 | F32: =+Transbank!B34 -> 0 | G32: =+Cuadratura!$K$35 -> 0 | H32: =VLOOKUP(A32,Resumen!$G$3:$H$54,2,0) -> #N/A | I32: =K31-M31 -> 0 | J32: =+D32-F32-H32+I32 -> #N/A | L32: =+K32-J32 -> #N/A

Sheet Delivery
D2: 20000 | F2: =D2*E2 -> 0
D3: 10000 | F3: =D3*E3 -> 0
D4: 5000 | F4: =D4*E4 -> 0
D5: 2000 | F5: =D5*E5 -> 0
D6: 1000 | F6: =D6*E6 -> 0
D7: 500 | F7: =D7*E7 -> 0
D8: 100 | F8: =D8*E8 -> 0
D9: 50 | F9: =D9*E9 -> 0
D10: 10 | F10: =D10*E10 -> 0 | H10: 2083
D11: 5 | F11: =D11*E11 -> 0 | H11: 1845
D12: 1 | F12: =D12*E12 -> 0

Sheet asistencia
B2: ASISTENCIA Y RETIROS | I2: PAGOS ADELANTOS
B4: lorenza | D4: Apoloneo | E4: yuliño | F4: claudio | G4: aldo | H4: palta
I5: ingreso | J5: salida | K5: horas | L5: total x dia | M5: total x dia de sueldo
A6: 44044 | I6: 12 | J6: 20 | K6: =J6-I6 -> 8 | L6: =K6*2000 -> 16000 | M6: =450000/30 -> 15000 | N6: =L6*24 -> 384000
A7: 44045
A8: 44046
A9: 44047
A10: 44048 | B10: falto y entro edwin
A11: 44049
A12: 44050
A13: 44051
A14: 44052 | J14: palta
A15: 44053
A16: 44054
A17: 44055
A18: 44056
A19: 44057
A20: 44058
A21: 44059
A22: 44060
A23: 44061 | H23: 10
A24: 44062 | D24: falto | E24: llego | H24: 5kilos
A25: 44063 | B25: llego | H25: 7kilos
A26: 44064 | B26: llego | E26: llego | H26: 10kilos
A27: 44065 | E27: llego | H27: 15kilos
A28: 44066 | H28: domingo
A29: 44067 | H29: karol
A30: 44068 | H30: karol
A31: 44069 | H31: 8
A32: 44070 | H32: 0
A33: 44071 | E33: LLEGO | H33: 15
A34: 44072
A35: 44073
A36: 44074

Sheet Resumen
A1: Ventas con Boleta | D1: Ventas sodexo ticket | G1: Retiros | J1: Ventas TRANSBANK | L1: diferencia
A3: Suma de Monto | D3: Suma de Monto | G3: Suma de Monto | J3: Suma de Monto
A4: Fecha | B4: Total | D4: Fecha | E4: Total | G4: Fecha | H4: Total | J4: Fecha | K4: Total
A5: 44409 | D5: 44409 | E5: 0 | G5: Total general | J5: 44409 | K5: 0
A6: 44410 | D6: 44410 | E6: 0 | J6: 44410 | K6: 0
A7: 44411 | D7: 44411 | E7: 0 | J7: 44411 | K7: 0
A8: 44412 | D8: 44412 | E8: 0 | J8: 44412 | K8: 0
A9: 44413 | D9: 44413 | E9: 0 | J9: 44413 | K9: 0
A10: 44414 | D10: 44414 | E10: 0 | J10: 44414 | K10: 0
A11: 44415 | D11: 44415 | E11: 0 | J11: 44415 | K11: 0
A12: 44416 | D12: 44416 | E12: 0 | J12: 44416 | K12: 0
A13: 44417 | D13: 44417 | E13: 0 | J13: 44417 | K13: 0
A14: 44418 | D14: 44418 | E14: 0 | J14: 44418 | K14: 0
A15: 44419 | D15: 44419 | E15: 0 | J15: 44419 | K15: 0
A16: 44420 | D16: 44420 | E16: 0 | J16: 44420 | K16: 0
A17: 44421 | D17: 44421 | E17: 0 | J17: 44421 | K17: 0
... A34: 44438 | D34: 44438 | E34: 0 | J34: 44438 | K34: 0
A35: 44439 | D35: 44439 | J35: 44439 | K35: 0
A36: Total general | D36: Total general | E36: 0 | J36: Total general | K36: 0

Sheet GASTOS
D2: gastos
C3: retiros efectivo | D3: monto | E3: descripcion
B4: 43831
B5: 43832
B6: 43833
B7: 43834
B8: 43835
B9: 43836
B10: 43837
B11: 43838
B12: 43839
B13: 43840
B14: 43841
B15: 43842
... B34: 43861
B35: TOTAL MEDIA
B36: TOTAL EFECTIVO
